hmmviz/__init__.py
hmmviz/base.py
hmmviz-0.0.7.dist-info/LICENSE
hmmviz-0.0.7.dist-info/METADATA
hmmviz-0.0.7.dist-info/WHEEL
hmmviz-0.0.7.dist-info/top_level.txt
hmmviz-0.0.7.dist-info/RECORD
