Metadata-Version: 2.1
Name: hmmviz
Version: 0.0.7
Summary: A package for visualizing state transition graphs from hidden Markov models or other models.
Home-page: https://github.com/benrussell80/hmmviz
Author: Benjamin Russell
License: UNKNOWN
Platform: UNKNOWN
Classifier: Programming Language :: Python :: 3
Classifier: License :: OSI Approved :: MIT License
Classifier: Operating System :: OS Independent
Requires-Python: >=3.6
Requires-Dist: hmmlearn (>=0.2)
Requires-Dist: matplotlib (>=3.1.0)
Requires-Dist: numpy (>=1.16)
Requires-Dist: pandas (>=0.24.2)
